CHANGES.rst
MANIFEST.in
README.rst
buildout.cfg
requirements-coverage.txt
requirements-tests.txt
setup.py
docs/HISTORY.txt
docs/LICENSE.GPL
docs/LICENSE.txt
docs/MIGRATION.txt
src/Products/__init__.py
src/Products.MeetingLalouviere.egg-info/PKG-INFO
src/Products.MeetingLalouviere.egg-info/SOURCES.txt
src/Products.MeetingLalouviere.egg-info/dependency_links.txt
src/Products.MeetingLalouviere.egg-info/namespace_packages.txt
src/Products.MeetingLalouviere.egg-info/not-zip-safe
src/Products.MeetingLalouviere.egg-info/requires.txt
src/Products.MeetingLalouviere.egg-info/top_level.txt
src/Products/MeetingLalouviere/README.txt
src/Products/MeetingLalouviere/__init__.py
src/Products/MeetingLalouviere/adapters.py
src/Products/MeetingLalouviere/config.py
src/Products/MeetingLalouviere/configure.zcml
src/Products/MeetingLalouviere/events.py
src/Products/MeetingLalouviere/events.zcml
src/Products/MeetingLalouviere/interfaces.py
src/Products/MeetingLalouviere/overrides.zcml
src/Products/MeetingLalouviere/profiles.zcml
src/Products/MeetingLalouviere/refresh.txt
src/Products/MeetingLalouviere/setuphandlers.py
src/Products/MeetingLalouviere/testing.py
src/Products/MeetingLalouviere/testing.zcml
src/Products/MeetingLalouviere/utils.py
src/Products/MeetingLalouviere/version.txt
src/Products/MeetingLalouviere/vocabularies.py
src/Products/MeetingLalouviere/vocabularies.zcml
src/Products/MeetingLalouviere/browser/__init__.py
src/Products/MeetingLalouviere/browser/configure.zcml
src/Products/MeetingLalouviere/browser/overrides.py
src/Products/MeetingLalouviere/browser/views.py
src/Products/MeetingLalouviere/browser/template/meeting_before_faceted_infos.pt
src/Products/MeetingLalouviere/locales/PloneMeeting.pot
src/Products/MeetingLalouviere/locales/imio.actionspanel.pot
src/Products/MeetingLalouviere/locales/imio.history.pot
src/Products/MeetingLalouviere/locales/plone.pot
src/Products/MeetingLalouviere/locales/sync_pos.sh
src/Products/MeetingLalouviere/locales/en/LC_MESSAGES/plone.po
src/Products/MeetingLalouviere/locales/fr/LC_MESSAGES/PloneMeeting.po
src/Products/MeetingLalouviere/locales/fr/LC_MESSAGES/imio.actionspanel.po
src/Products/MeetingLalouviere/locales/fr/LC_MESSAGES/imio.history.po
src/Products/MeetingLalouviere/locales/fr/LC_MESSAGES/plone.po
src/Products/MeetingLalouviere/migrations/__init__.py
