Metadata-Version: 2.1
Name: Products.MeetingLalouviere
Version: 4.2.14
Summary: Official meetings management for college and council custom profile for La Louvière
Home-page: http://www.imio.be/produits/gestion-des-deliberations
Author: Olivier Delaere
Author-email: olivier.delaere@imio.be
License: GPL
Platform: UNKNOWN
Classifier: Environment :: Web Environment
Classifier: Framework :: Plone
Classifier: Framework :: Plone :: 4.3
Classifier: License :: OSI Approved :: GNU General Public License (GPL)
Classifier: Programming Language :: Python
Classifier: Programming Language :: Python :: 2.7
Provides-Extra: templates
Provides-Extra: test
